ktg/__init__.py
ktg/parse_mode.py
ktg/telegram.py
ktg-0.0.9.dist-info/METADATA
ktg-0.0.9.dist-info/WHEEL
ktg-0.0.9.dist-info/top_level.txt
ktg-0.0.9.dist-info/RECORD
