Metadata-Version: 2.1
Name: ktg
Version: 0.0.9
Summary: send telegram message
Home-page: https://github.com/kkristof200/py_telegram_send
Author: Kristof
License: UNKNOWN
Platform: UNKNOWN
Classifier: Programming Language :: Python :: 3
Classifier: License :: OSI Approved :: MIT License
Classifier: Operating System :: OS Independent
Requires-Python: >=3.5
Requires-Dist: kcu (>=0.0.66)
